dave_vessels/__init__.cp312-win_amd64.pyd
dave_vessels/deck_cargo_nodes.cp312-win_amd64.pyd
dave_vessels/element_types.cp312-win_amd64.pyd
dave_vessels/super_elements.cp312-win_amd64.pyd
dave_vessels/analysis/__init__.cp312-win_amd64.pyd
dave_vessels/analysis/coefficients.cp312-win_amd64.pyd
dave_vessels/analysis/mooring.cp312-win_amd64.pyd
dave_vessels/analysis/mooring_LRFD.cp312-win_amd64.pyd
dave_vessels/analysis/stability.cp312-win_amd64.pyd
dave_vessels/annotations/__init__.cp312-win_amd64.pyd
dave_vessels/annotations/mooring_layers.cp312-win_amd64.pyd
dave_vessels/gui/__init__.cp312-win_amd64.pyd
dave_vessels/gui/thumbnail_maker.cp312-win_amd64.pyd
dave_vessels/gui/docks/__init__.cp312-win_amd64.pyd
dave_vessels/gui/docks/decklayout.cp312-win_amd64.pyd
dave_vessels/gui/docks/dock_ballast2dview.cp312-win_amd64.pyd
dave_vessels/gui/docks/dock_mooring.cp312-win_amd64.pyd
dave_vessels/gui/docks/widget_ballastconfiguration.cp312-win_amd64.pyd
dave_vessels/gui/docks/widget_ballastsolver.cp312-win_amd64.pyd
dave_vessels/gui/docks/widget_ballastsystemselect.cp312-win_amd64.pyd
dave_vessels/gui/docks/widget_tank_order.cp312-win_amd64.pyd
dave_vessels/gui/forms/__init__.cp312-win_amd64.pyd
dave_vessels/gui/forms/dock_decklayout.cp312-win_amd64.pyd
dave_vessels/gui/forms/dock_mooring.cp312-win_amd64.pyd
dave_vessels/gui/forms/node_vessel.cp312-win_amd64.pyd
dave_vessels/gui/forms/resources_rc.cp312-win_amd64.pyd
dave_vessels/gui/forms/section_ballast_steps.cp312-win_amd64.pyd
dave_vessels/gui/forms/section_stability.cp312-win_amd64.pyd
dave_vessels/gui/forms/section_sustainable_wind.cp312-win_amd64.pyd
dave_vessels/gui/forms/widgetUI_ballastconfiguration.cp312-win_amd64.pyd
dave_vessels/gui/forms/widgetUI_ballastsolver.cp312-win_amd64.pyd
dave_vessels/gui/forms/widgetUI_tank_order.cp312-win_amd64.pyd
dave_vessels/gui/nodes/__init__.cp312-win_amd64.pyd
dave_vessels/gui/nodes/vessel.cp312-win_amd64.pyd
dave_vessels/gui/sections/__init__.cp312-win_amd64.pyd
dave_vessels-2025.0.6.dist-info/licenses/LICENSE.txt
dave_vessels-2025.0.6.dist-info/METADATA
dave_vessels-2025.0.6.dist-info/WHEEL
dave_vessels-2025.0.6.dist-info/top_level.txt
dave_vessels-2025.0.6.dist-info/RECORD
